physicar/__init__.py
physicar/cloud/__init__.py
physicar/cloud/deepracer/__init__.py
physicar/cloud/deepracer/app.py
physicar/cloud/deepracer/config.py
physicar/cloud/deepracer/debug_reward.py
physicar/cloud/deepracer/drfc_writer.py
physicar/cloud/deepracer/i18n.py
physicar/cloud/deepracer/jobs.py
physicar/cloud/deepracer/schemas.py
physicar/cloud/deepracer/settings_manager.py
physicar/cloud/deepracer/analysis/__init__.py
physicar/cloud/deepracer/analysis/action_space.py
physicar/cloud/deepracer/analysis/load.py
physicar/cloud/deepracer/data/params_logs/HB-continuous.pkl
physicar/cloud/deepracer/data/params_logs/HB-discrete.pkl
physicar/cloud/deepracer/data/params_logs/OA-continuous.pkl
physicar/cloud/deepracer/data/params_logs/OA-discrete.pkl
physicar/cloud/deepracer/data/params_logs/TT-continuous.pkl
physicar/cloud/deepracer/data/params_logs/TT-discrete.pkl
physicar/cloud/deepracer/data/tracks/tracks_description_trans.yaml
physicar/cloud/deepracer/data/tracks/tracks_info.yml
physicar/cloud/deepracer/data/tracks/npy/2022_april_open.npy
physicar/cloud/deepracer/data/tracks/npy/2022_april_open_ccw.npy
physicar/cloud/deepracer/data/tracks/npy/2022_april_open_cw.npy
physicar/cloud/deepracer/data/tracks/npy/2022_april_pro.npy
physicar/cloud/deepracer/data/tracks/npy/2022_april_pro_ccw.npy
physicar/cloud/deepracer/data/tracks/npy/2022_april_pro_cw.npy
physicar/cloud/deepracer/data/tracks/npy/2022_august_open.npy
physicar/cloud/deepracer/data/tracks/npy/2022_august_open_ccw.npy
physicar/cloud/deepracer/data/tracks/npy/2022_august_open_cw.npy
physicar/cloud/deepracer/data/tracks/npy/2022_august_pro.npy
physicar/cloud/deepracer/data/tracks/npy/2022_august_pro_ccw.npy
physicar/cloud/deepracer/data/tracks/npy/2022_august_pro_cw.npy
physicar/cloud/deepracer/data/tracks/npy/2022_july_open.npy
physicar/cloud/deepracer/data/tracks/npy/2022_july_pro.npy
physicar/cloud/deepracer/data/tracks/npy/2022_july_pro_ccw.npy
physicar/cloud/deepracer/data/tracks/npy/2022_july_pro_cw.npy
physicar-1.0.5.dist-info/licenses/LICENSE
physicar-1.0.5.dist-info/METADATA
physicar-1.0.5.dist-info/WHEEL
physicar-1.0.5.dist-info/top_level.txt
physicar-1.0.5.dist-info/RECORD
