Metadata-Version: 2.4
Name: physicar
Version: 1.0.5
Summary: Physicar Python SDK
Home-page: https://github.com/physicar/physicar-python
Author: AI Castle
Author-email: dev@aicastle.com
License: Apache-2.0
Classifier: Programming Language :: Python :: 3
Classifier: License :: OSI Approved :: Apache Software License
Classifier: Operating System :: OS Independent
Requires-Python: >=3.8
License-File: LICENSE
Provides-Extra: cloud-deepracer
Requires-Dist: fastapi>=0.100.0; extra == "cloud-deepracer"
Requires-Dist: uvicorn[standard]>=0.23.0; extra == "cloud-deepracer"
Requires-Dist: jinja2>=3.0.0; extra == "cloud-deepracer"
Requires-Dist: python-multipart>=0.0.6; extra == "cloud-deepracer"
Requires-Dist: boto3>=1.26.0; extra == "cloud-deepracer"
Requires-Dist: minio>=7.0.0; extra == "cloud-deepracer"
Requires-Dist: pyyaml>=6.0; extra == "cloud-deepracer"
Requires-Dist: aiohttp>=3.8.0; extra == "cloud-deepracer"
Requires-Dist: aiofiles>=23.0.0; extra == "cloud-deepracer"
Requires-Dist: requests>=2.28.0; extra == "cloud-deepracer"
Requires-Dist: pillow>=9.0.0; extra == "cloud-deepracer"
Requires-Dist: pytz>=2023.0; extra == "cloud-deepracer"
Requires-Dist: jsonschema>=4.0.0; extra == "cloud-deepracer"
Requires-Dist: itsdangerous>=2.0.0; extra == "cloud-deepracer"
Requires-Dist: pandas>=2.0.0; extra == "cloud-deepracer"
Requires-Dist: matplotlib>=3.7.0; extra == "cloud-deepracer"
Requires-Dist: numpy>=1.24.0; extra == "cloud-deepracer"
Requires-Dist: opencv-python-headless>=4.8.0; extra == "cloud-deepracer"
Dynamic: license-file
